fortuneluckpredictor/__init__.py
fortuneluckpredictor/__main__.py
fortuneluckpredictor/compatibility_score.py
fortuneluckpredictor/fortune.py
fortuneluckpredictor/futurePredictions.py
fortuneluckpredictor/luckyNumber.py
fortuneluckpredictor/predictDay.py
fortuneluckpredictor-1.0.2.dist-info/licenses/LICENSE
fortuneluckpredictor-1.0.2.dist-info/METADATA
fortuneluckpredictor-1.0.2.dist-info/WHEEL
fortuneluckpredictor-1.0.2.dist-info/top_level.txt
fortuneluckpredictor-1.0.2.dist-info/RECORD
