Metadata-Version: 2.4
Name: fortuneluckpredictor
Version: 1.0.2
Summary: Fortune & luck predictor. Returns lucky numbers, fortunes, and horoscope-like results.
Author-email: "Pranathi Chinthalapani, Sam Rawdon, May Zhou, Hanjun Deng, William Chan" <prc9852@nyu.edu>, Pranathi Chinthalapani <prc9852@nyu.edu>, Sam Rawdon <sr6360@nyu.edu>, May Zhou <zz4206@nyu.edu>, Hanjun Deng <hd2432@nyu.edu>, William Chan <wc2184@nyu.edu>
License-Expression: GPL-3.0
Project-URL: Homepage, https://github.com/swe-students-fall2025/3-python-package-team_boreal
Project-URL: Repository, https://github.com/swe-students-fall2025/3-python-package-team_boreal.git
Project-URL: Issues, https://github.com/swe-students-fall2025/3-python-package-team_boreal/issues
Keywords: python,package,build,cookie,fun,guess,luck,fortune
Classifier: Programming Language :: Python :: 3
Classifier: Operating System :: OS Independent
Requires-Python: >=3.9
License-File: LICENSE
Provides-Extra: dev
Requires-Dist: pytest; extra == "dev"
Dynamic: license-file
